holiday/__init__.py
holiday/_compat.py
holiday/core.py
holiday/exceptions.py
holiday-1.0.0.dist-info/DESCRIPTION.rst
holiday-1.0.0.dist-info/METADATA
holiday-1.0.0.dist-info/metadata.json
holiday-1.0.0.dist-info/RECORD
holiday-1.0.0.dist-info/top_level.txt
holiday-1.0.0.dist-info/WHEEL
