Metadata-Version: 1.1
Name: holiday
Version: 1.0.0
Summary: holiday is a package to generate holiday.
Home-page: https://github.com/wanshot/holiday
Author: wanshot
Author-email: nishikawa0228@sj9.so-net.ne.jp
License: ('MIT License',)
Keywords: datetime,date,time,calendar
Platform: UNKNOWN
Classifier: License :: OSI Approved :: MIT License
Classifier: Programming Language :: Python
Classifier: Development Status :: 5 - Production/Stable
Classifier: Topic :: Software Development
Classifier: Programming Language :: Python :: 2
